setup.py
ezretry/__init__.py
ezretry/api.py
ezretry/core.py
ezretry.egg-info/PKG-INFO
ezretry.egg-info/SOURCES.txt
ezretry.egg-info/dependency_links.txt
ezretry.egg-info/entry_points.txt
ezretry.egg-info/top_level.txt