Metadata-Version: 1.0
Name: ezretry
Version: 1.0.0
Summary: Not only simply retry, it will call a function for user define Exceptions before retry
Home-page: https://github.com/cnkailyn/ezretry
Author: kailyn
Author-email: 1074741118@qq.com
License: UNKNOWN
Keywords: retry,ezretry
Platform: UNKNOWN
